pyasmgen/__init__.py
pyasmgen/code.py
pyasmgen/instructions.py
pyasmgen/pseudos.py
pyasmgen/blocks/__init__.py
pyasmgen/blocks/base.py
pyasmgen/blocks/useful.py
pyasmgen/utils/__init__.py
pyasmgen/utils/block.py
pyasmgen/utils/instruction.py
pyasmgen/utils/pseudo.py
pyasmgen-0.1.1.dist-info/licenses/LICENSE
pyasmgen-0.1.1.dist-info/METADATA
pyasmgen-0.1.1.dist-info/WHEEL
pyasmgen-0.1.1.dist-info/top_level.txt
pyasmgen-0.1.1.dist-info/RECORD
