Metadata-Version: 2.4
Name: pyasmgen
Version: 0.1.1
Summary: Python-based 8051 Assembly Code Generator.
Author-email: Albus Shore <dev@albus-shore.net>
License: MIT
Project-URL: Homepage, https://github.com/albus-shore/PyASMGen
Project-URL: Repository, https://github.com/albus-shore/PyASMGen
Requires-Python: >=3.8
License-File: LICENSE
Dynamic: license-file
